configgery/__init__.py
configgery/client.py
configgery/configurations_metadata.py
configgery/file.py
configgery_client-2.2.0.dist-info/LICENSE
configgery_client-2.2.0.dist-info/METADATA
configgery_client-2.2.0.dist-info/WHEEL
configgery_client-2.2.0.dist-info/RECORD
