Metadata-Version: 2.1
Name: configgery-client
Version: 2.2.0
Summary: Python client for devices interacting with configgery.com
Home-page: https://configgery.com
License: MIT
Author: Robert Weiss
Author-email: rob@configgery.com
Requires-Python: >=3.8,<4.0
Classifier: License :: OSI Approved :: MIT License
Classifier: Programming Language :: Python :: 3
Classifier: Programming Language :: Python :: 3.8
Classifier: Programming Language :: Python :: 3.9
Classifier: Programming Language :: Python :: 3.10
Classifier: Programming Language :: Python :: 3.11
Classifier: Programming Language :: Python :: 3.12
Requires-Dist: urllib3 (>=2.1.0,<3.0.0)
Project-URL: Repository, https://github.com/Configgery/configgery-client-python
